parrot/__init__.py
parrot/_version.py
parrot/cli.py
parrot/conf.py
parrot/exceptions.c
parrot/exceptions.cpython-311-x86_64-linux-gnu.so
parrot/exceptions.pxd
parrot/exceptions.pxi
parrot/exceptions.pyx
parrot/py.typed
parrot/version.py
parrot/a2a/__init__.py
parrot/a2a/client.py
parrot/a2a/mesh.py
parrot/a2a/mixin.py
parrot/a2a/models.py
parrot/a2a/orchestrator.py
parrot/a2a/router.py
parrot/a2a/security.py
parrot/a2a/server.py
parrot/advisors/__init__.py
parrot/advisors/generator.py
parrot/advisors/manager.py
parrot/advisors/mixin.py
parrot/advisors/models.py
parrot/advisors/questions.py
parrot/advisors/state.py
parrot/advisors/catalog/__init__.py
parrot/advisors/catalog/catalog.py
parrot/advisors/catalog/example.sql
parrot/advisors/catalog/loaders.py
parrot/advisors/catalog/schema.py
parrot/advisors/tools/__init__.py
parrot/advisors/tools/base.py
parrot/advisors/tools/compare.py
parrot/advisors/tools/criteria.py
parrot/advisors/tools/image.py
parrot/advisors/tools/question.py
parrot/advisors/tools/recommend.py
parrot/advisors/tools/search.py
parrot/advisors/tools/start.py
parrot/advisors/tools/state.py
parrot/advisors/tools/undo.py
parrot/advisors/tools/utils.py
parrot/agents/__init__.py
parrot/autonomous/__init__.py
parrot/autonomous/evb.py
parrot/autonomous/example.py
parrot/autonomous/orchestrator.py
parrot/autonomous/redis_jobs.py
parrot/autonomous/scheduler.py
parrot/autonomous/webhooks.py
parrot/bots/__init__.py
parrot/bots/a2a_agent.py
parrot/bots/abstract.py
parrot/bots/agent.py
parrot/bots/base.py
parrot/bots/basic.py
parrot/bots/chatbot.py
parrot/bots/data.py
parrot/bots/document.py
parrot/bots/hrbot.py
parrot/bots/jira_specialist.py
parrot/bots/kb.py
parrot/bots/mcp.py
parrot/bots/product.py
parrot/bots/voice.py
parrot/bots/webdev.py
parrot/bots/database/__init__.py
parrot/bots/database/abstract.py
parrot/bots/database/cache.py
parrot/bots/database/models.py
ai_parrot-0.20.4.dist-info/METADATA
ai_parrot-0.20.4.dist-info/WHEEL
ai_parrot-0.20.4.dist-info/entry_points.txt
ai_parrot-0.20.4.dist-info/top_level.txt
ai_parrot-0.20.4.dist-info/RECORD
ai_parrot-0.20.4.dist-info/licenses/LICENSE
